petro_py/__init__.py
petro_py/oilField/__init__.py
petro_py/oilField/general_info.py
petro_py/oilField/oilfield.py
petro_py/production/__init__.py
petro_py/production/production.py
petro_py/reservoir/__init__.py
petro_py/reservoir/reservoir.py
petro_python-1.0.2.dist-info/LICENSE
petro_python-1.0.2.dist-info/METADATA
petro_python-1.0.2.dist-info/WHEEL
petro_python-1.0.2.dist-info/top_level.txt
petro_python-1.0.2.dist-info/RECORD
