Metadata-Version: 2.1
Name: petro-python
Version: 1.0.2
Summary: A python package for pteroleum computation
Home-page: https://github.com/Ahmed-Alkhatim/petro-python
Author: alkhatim
Author-email: alkhatim40@gmail.com
Project-URL: Bug Tracker, https://github.com/Ahmed-Alkhatim/petro-python/issues
Classifier: Programming Language :: Python :: 3
Classifier: License :: OSI Approved :: MIT License
Classifier: Operating System :: OS Independent
Requires-Python: >=3.6
License-File: LICENSE
